naylence/fame/channel/__init__.py
naylence/fame/channel/flow_controller.py
naylence/fame/channel/in_memory/__init__.py
naylence/fame/channel/in_memory/in_memory_binding.py
naylence/fame/channel/in_memory/in_memory_channel.py
naylence/fame/channel/in_memory/in_memory_fanout_broker.py
naylence/fame/config/__init__.py
naylence/fame/config/config.py
naylence/fame/config/peer_config.py
naylence/fame/connector/__init__.py
naylence/fame/connector/base_async_connector.py
naylence/fame/connector/base_http_listener.py
naylence/fame/connector/connector_config.py
naylence/fame/connector/connector_factory.py
naylence/fame/connector/connector_state.py
naylence/fame/connector/default_http_server.py
naylence/fame/connector/default_http_server_factory.py
naylence/fame/connector/grant_selection_policy.py
naylence/fame/connector/http_listener.py
naylence/fame/connector/http_listener_factory.py
naylence/fame/connector/http_server.py
naylence/fame/connector/http_server_config.py
naylence/fame/connector/http_server_factory.py
naylence/fame/connector/http_stateless_connector.py
naylence/fame/connector/http_stateless_connector_factory.py
naylence/fame/connector/transport_listener.py
naylence/fame/connector/transport_listener_config.py
naylence/fame/connector/transport_listener_factory.py
naylence/fame/connector/websocket_connector.py
naylence/fame/connector/websocket_connector_factory.py
naylence/fame/connector/websocket_listener.py
naylence/fame/connector/websocket_listener_factory.py
naylence/fame/constants/ttl_constants.py
naylence/fame/delivery/at_least_once_delivery_policy.py
naylence/fame/delivery/at_least_once_delivery_policy_factory.py
naylence/fame/delivery/at_most_once_delivery_policy.py
naylence/fame/delivery/at_most_once_delivery_policy_factory.py
naylence/fame/delivery/default_delivery_tracker.py
naylence/fame/delivery/default_delivery_tracker_factory.py
naylence/fame/delivery/delivery_policy.py
naylence/fame/delivery/delivery_policy_factory.py
naylence_runtime-0.4.11.dist-info/METADATA
naylence_runtime-0.4.11.dist-info/WHEEL
naylence_runtime-0.4.11.dist-info/entry_points.txt
naylence_runtime-0.4.11.dist-info/licenses/LICENSE
naylence_runtime-0.4.11.dist-info/licenses/NOTICE
naylence_runtime-0.4.11.dist-info/RECORD
