Metadata-Version: 2.4
Name: naylence-runtime
Version: 0.4.11
Summary: Naylence Runtime
License: Apache-2.0
License-File: LICENSE
License-File: NOTICE
Keywords: messaging,ai,agents,platform,naylence
Author: naylencedev@gmail.com
Requires-Python: >=3.12
Classifier: Development Status :: 4 - Beta
Classifier: Intended Audience :: Developers
Classifier: License :: OSI Approved :: Apache Software License
Classifier: Programming Language :: Python :: 3
Classifier: Programming Language :: Python :: 3.12
Classifier: Topic :: Software Development :: Libraries :: Python Modules
Classifier: Topic :: System :: Distributed Computing
Requires-Dist: aiohttp (>=3.11.18,<4.0.0)
Requires-Dist: cryptography (>=45.0.6,<46.0.0)
Requires-Dist: fastapi (>=0.116.1,<0.117.0)
Requires-Dist: httpx (>=0.28.1,<0.29.0)
Requires-Dist: naylence-core (>=0.3.3,<0.4.0)
Requires-Dist: pyjwt (>=2.10.1,<3.0.0)
Requires-Dist: python-multipart (>=0.0.20,<0.0.21)
Requires-Dist: pyyaml (>=6.0.2,<7.0.0)
Requires-Dist: structlog (>=25.3.0,<26.0.0)
Requires-Dist: uvicorn (>=0.35.0,<0.36.0)
Requires-Dist: websockets (>=15.0.1,<16.0.0)
Project-URL: Bug Tracker, https://github.com/naylence/naylence-runtime-python/issues
Project-URL: Documentation, https://github.com/naylence/naylence-runtime-python#readme
Project-URL: Homepage, https://github.com/naylence/naylence-runtime-python
Project-URL: Repository, https://github.com/naylence/naylence-runtime-python
